mathoptdev/__init__.py
mathoptdev/auth.py
mathoptdev/cli.py
mathoptdev/collection.py
mathoptdev/create_jobs.py
mathoptdev/logger.py
mathoptdev/login.py
mathoptdev/logout.py
mathoptdev/miplib.py
mathoptdev/process_queue.py
mathoptdev/py.typed
mathoptdev/queries.py
mathoptdev/queue_jobs.py
mathoptdev/send_request.py
mathoptdev/send_stream_request.py
mathoptdev/token.py
mathoptdev/types.py
mathoptdev/upload.py
mathoptdev/utils.py
mathoptdev/config/__init__.py
mathoptdev/config/dev.py
mathoptdev/config/prod.py
mathoptdev/instance_generator/tsp.py
mathoptdev-0.1.5.dist-info/METADATA
mathoptdev-0.1.5.dist-info/WHEEL
mathoptdev-0.1.5.dist-info/entry_points.txt
mathoptdev-0.1.5.dist-info/RECORD
