Metadata-Version: 2.4
Name: mathoptdev
Version: 0.1.5
Summary: Python CLI and SDK for mathopt.dev the platform for mathematical optimization
Author-email: Charly Larocca <larocca.charly@gmail.com>
Requires-Python: >=3.12
Requires-Dist: click>=8.1.8
Requires-Dist: colorlog>=6.9.0
Requires-Dist: pandas>=2.2.3
Requires-Dist: pyarrow>=19.0.0
Requires-Dist: pydantic>=2.10.6
Requires-Dist: python-dotenv>=1.0.1
Requires-Dist: requests>=2.32.3
Requires-Dist: tqdm>=4.67.1
